xml2python/__init__.py
xml2python/_version.py
xml2python/xml2python.py
xml2python-0.1.1.dist-info/METADATA
xml2python-0.1.1.dist-info/WHEEL
xml2python-0.1.1.dist-info/licenses/LICENCE.txt
xml2python-0.1.1.dist-info/RECORD
