Metadata-Version: 2.4
Name: xml2python
Version: 0.1.1
Summary: xml2python is a simple helper class to transform XML input to more usable python dicts.
Project-URL: Homepage, https://github.com/binary-butterfly/xml2python
Project-URL: Repository, https://github.com/binary-butterfly/xml2python.git
Project-URL: Issues, https://github.com/binary-butterfly/xml2python/issues
Project-URL: Changelog, https://github.com/binary-butterfly/xml2python/blob/main/CHANGELOG.md
Author-email: "Ernesto Ruge, binary butterfly GmbH" <ernesto.ruge@binary-butterfly.de>
Maintainer-email: "Ernesto Ruge, binary butterfly GmbH" <ernesto.ruge@binary-butterfly.de>
License-File: LICENCE.txt
Keywords: data,dict,xml
Classifier: Development Status :: 3 - Alpha
Classifier: Intended Audience :: Developers
Classifier: License :: OSI Approved :: MIT License
Classifier: Operating System :: OS Independent
Classifier: Programming Language :: Python :: 3
Classifier: Programming Language :: Python :: 3.10
Classifier: Programming Language :: Python :: 3.11
Classifier: Programming Language :: Python :: 3.12
Classifier: Programming Language :: Python :: Implementation :: CPython
Classifier: Topic :: Software Development :: Libraries :: Python Modules
Classifier: Topic :: Utilities
Requires-Python: >=3.10
Requires-Dist: lxml~=5.4.0
Provides-Extra: testing
Requires-Dist: pytest-cov~=6.1.1; extra == 'testing'
Requires-Dist: pytest~=8.3.5; extra == 'testing'
Requires-Dist: ruff~=0.11.10; extra == 'testing'
